setup.py
ebs/__init__.py
ebs/args.py
ebs/filesys.py
ebs/imports.py
ebs/merge_cols.py
ebs/read_indata.py
ebs/sort_outcols.py
ebs/split_filelist.py
ebs/stats.py
ebs/version.py
ebs.egg-info/PKG-INFO
ebs.egg-info/SOURCES.txt
ebs.egg-info/dependency_links.txt
ebs.egg-info/requires.txt
ebs.egg-info/top_level.txt